LICENSE.txt
README.md
pyproject.toml
stickytext/__init__.py
stickytext/__main__.py
stickytext/app.py
stickytext/window/__init__.py
stickytext/window/window.cmb
stickytext/window/window.py
stickytext/window/window.ui
stickytext-0.1.0.dist-info/entry_points.txt
stickytext-0.1.0.dist-info/LICENSE.txt
stickytext-0.1.0.dist-info/WHEEL
stickytext-0.1.0.dist-info/METADATA
stickytext-0.1.0.dist-info/RECORD
