Metadata-Version: 2.1
Name: stickytext
Version: 0.1.0
Summary: An extremely simple app for showing a text file as a sticky note
Home-page: https://github.com/BeatLink/StickyText
License: GPL-3.0-or-later
Keywords: note,notes,autosave,gtk,text,sticky,linux
Author: BeatLink
Author-email: beatlink+git@simplelogin.co
Requires-Python: >=3.10,<4.0
Classifier: Development Status :: 3 - Alpha
Classifier: Environment :: X11 Applications :: GTK
Classifier: Intended Audience :: End Users/Desktop
Classifier: License :: OSI Approved :: GNU General Public License v3 or later (GPLv3+)
Classifier: Natural Language :: English
Classifier: Operating System :: POSIX :: Linux
Classifier: Programming Language :: Python
Classifier: Programming Language :: Python :: 3
Classifier: Programming Language :: Python :: 3.10
Requires-Dist: pygobject (>=3.42.1,<4.0.0)
Requires-Dist: setuptools (>=67.7.1,<68.0.0)
Project-URL: Bug Tracker, https://github.com/BeatLink/StickyText/-/issues
Project-URL: Documentation, https://github.com/BeatLink/StickyText
Project-URL: Repository, https://github.com/BeatLink/StickyText
